scikit_pns-1.2.0.dist-info/licenses/LICENSE
skpns/__init__.py
skpns/onnx.py
skpns/pns.py
skpns/sklearn.py
skpns/util.py
scikit_pns-1.2.0.dist-info/METADATA
scikit_pns-1.2.0.dist-info/WHEEL
scikit_pns-1.2.0.dist-info/top_level.txt
scikit_pns-1.2.0.dist-info/RECORD
