Metadata-Version: 2.4
Name: scikit-pns
Version: 1.2.0
Summary: Principal nested spheres (PNS) analysis
Author-email: Jisoo Song <jeesoo9595@snu.ac.kr>
License-Expression: MIT
Project-URL: homepage, https://pypi.python.org/pypi/scikit-pns/
Project-URL: source, https://github.com/JSS95/scikit-pns
Project-URL: documentation, https://scikit-pns.readthedocs.io
Classifier: Development Status :: 5 - Production/Stable
Classifier: Intended Audience :: Science/Research
Classifier: Programming Language :: Python
Classifier: Programming Language :: Python :: 3
Classifier: Programming Language :: Python :: 3.10
Classifier: Programming Language :: Python :: 3.11
Classifier: Programming Language :: Python :: 3.12
Classifier: Programming Language :: Python :: 3 :: Only
Classifier: Topic :: Scientific/Engineering
Classifier: Operating System :: OS Independent
Requires-Python: >=3.10
License-File: LICENSE
Requires-Dist: numpy
Requires-Dist: scipy
Requires-Dist: scikit-learn
Provides-Extra: onnx
Requires-Dist: skl2onnx; extra == "onnx"
Provides-Extra: test
Requires-Dist: pytest; extra == "test"
Requires-Dist: onnxruntime; extra == "test"
Requires-Dist: scikit-pns[onnx]; extra == "test"
Provides-Extra: doc
Requires-Dist: sphinx; extra == "doc"
Requires-Dist: numpydoc; extra == "doc"
Requires-Dist: pydata_sphinx_theme; extra == "doc"
Requires-Dist: matplotlib; extra == "doc"
Requires-Dist: onnxruntime; extra == "doc"
Requires-Dist: scikit-pns[onnx]; extra == "doc"
Provides-Extra: dev
Requires-Dist: flake8; extra == "dev"
Requires-Dist: black; extra == "dev"
Requires-Dist: isort; extra == "dev"
Requires-Dist: scikit-pns[doc,test]; extra == "dev"
Dynamic: license-file
